icon/addr.ico
icon/all.ico
icon/author.ico
icon/destination.ico
icon/download.ico
icon/exit.ico
icon/false.ico
icon/filter.ico
icon/gateway.ico
icon/global.ico
icon/help.ico
icon/io.ico
icon/ip.ico
icon/layer.ico
icon/loading.png
icon/local.ico
icon/mac.ico
icon/open.ico
icon/packageRecv.ico
icon/packageSent.ico
icon/protocol.ico
icon/prots.ico
icon/rank.ico
icon/refresh.ico
icon/remote.ico
icon/restart.ico
icon/save.ico
icon/source.ico
icon/spruce.ico
icon/spruce.png
icon/spurce.icoo
icon/start.ico
icon/stop.ico
icon/tcp.ico
icon/true.ico
icon/type.ico
icon/udp.ico
icon/updown.ico
icon/upload.ico
icon/vendor.ico
src/__main__.py
src/capturePkt/__init__.py
src/capturePkt/arp.py
src/capturePkt/cookedPacket.py
src/capturePkt/dhcp.py
src/capturePkt/domain.py
src/capturePkt/eapol.py
src/capturePkt/ethernet.py
src/capturePkt/general.py
src/capturePkt/hopopt.py
src/capturePkt/icmp.py
src/capturePkt/icmpv6.py
src/capturePkt/igmp.py
src/capturePkt/ipv4.py
src/capturePkt/ipv6.py
src/capturePkt/networkProtocol.py
src/capturePkt/ntp.py
src/capturePkt/pppoed.py
src/capturePkt/pppoes.py
src/capturePkt/publicApp.py
src/capturePkt/roughPacket.py
src/capturePkt/tcp.py
src/capturePkt/telnet.py
src/capturePkt/tftp.py
src/capturePkt/udp.py
src/dialogs/__init__.py
src/dialogs/authorDialog.py
src/dialogs/filterDialog.py
src/dialogs/helpDialog.py
src/dialogs/loadDialog.py
src/dialogs/nodeDialog.py
src/dialogs/rankDialog.py
src/dialogs/shineDialog.py
src/dialogs/statisticDialog.py
src/threads/__init__.py
src/threads/captureThread.py
src/threads/openThread.py
src/threads/parseThread.py
src/threads/poisonThread.py
src/threads/queryThread.py
src/threads/saveThread.py
src/threads/scanThread.py
src/threads/searchThread.py
src/threads/termsThread.py
src/threads/trafficThread.py
src/windows/__init__.py
src/windows/brightMainWindow.py
src/windows/mainWindow.py
src/windows/shineMainWindow.py
static/help.html
static/oui.csv
spruce_sniffer-0.1.5.dist-info/LICENSE
spruce_sniffer-0.1.5.dist-info/METADATA
spruce_sniffer-0.1.5.dist-info/WHEEL
spruce_sniffer-0.1.5.dist-info/entry_points.txt
spruce_sniffer-0.1.5.dist-info/top_level.txt
spruce_sniffer-0.1.5.dist-info/RECORD
