Metadata-Version: 2.1
Name: spruce-sniffer
Version: 0.1.5
Summary: spruce sniffer is a versatile network sniffer
Home-page: https://github.com/Alopex4/spruce
Author: alopex cheung
Author-email: alopex4@163.com
License: MIT
Platform: UNKNOWN
Classifier: Natural Language :: English
Classifier: Operating System :: POSIX :: Linux
Classifier: License :: OSI Approved :: MIT License
Classifier: Programming Language :: Python :: 3.5
Classifier: Programming Language :: Python :: 3 :: Only
Classifier: Programming Language :: Python :: Implementation :: CPython
Classifier: Topic :: System :: Networking :: Monitoring
Classifier: Topic :: Software Development :: Version Control :: Git
Requires-Dist: PyQt5 (>=5.12.1)
Requires-Dist: requests (>=2.21.0)
Requires-Dist: netifaces (>=0.10.9)
Requires-Dist: numpy (>=1.11.0)
Requires-Dist: matplotlib (>=3.0.3)
Requires-Dist: scapy (==2.4.0)
Requires-Dist: psutil (>=3.4.2)
Requires-Dist: ptable (>=0.9.2)
